garantipay_payment/__init__.py
garantipay_payment/forms.py
garantipay_payment/urls.py
garantipay_payment/views.py
garantipay_payment/commerce/__init__.py
garantipay_payment/commerce/checkout.py
garantipay_payment/commerce/dummy.py
garantipay_payment/templates/garantipay.html
garantipay_payment/tests/__init__.py
garantipay_payment/tests/mixins.py
garantipay_payment/tests/test_service.py
garantipay_payment/tests/test_views.py
garantipay_payment-2.0.0.dist-info/METADATA
garantipay_payment-2.0.0.dist-info/WHEEL
garantipay_payment-2.0.0.dist-info/top_level.txt
garantipay_payment-2.0.0.dist-info/RECORD
