Metadata-Version: 2.4
Name: garantipay-payment
Version: 2.0.0
Summary: A library to provide payment gateway for GarantiPay 2.0
Home-page: https://bitbucket.org/akinonteam/garantipay-payment
Author: Akinon
Author-email: dev@akinon.com
Requires-Dist: Django<4.3,>=2.2.9
Requires-Dist: requests
Requires-Dist: djangorestframework<4.0,>=3.14.0
Requires-Dist: mock==4.0.3
Dynamic: author
Dynamic: author-email
Dynamic: description
Dynamic: description-content-type
Dynamic: home-page
Dynamic: requires-dist
Dynamic: summary
